hmm/__init__.py
hmm/__main__.py
hiss_me_maybe-0.1.0.dist-info/entry_points.txt
hiss_me_maybe-0.1.0.dist-info/LICENSE
hiss_me_maybe-0.1.0.dist-info/METADATA
hiss_me_maybe-0.1.0.dist-info/WHEEL
hiss_me_maybe-0.1.0.dist-info/RECORD
